fds/__init__.py
fds/sdk/__init__.py
fds/sdk/ContentFeedsDataDictionary/__init__.py
fds/sdk/ContentFeedsDataDictionary/api_client.py
fds/sdk/ContentFeedsDataDictionary/configuration.py
fds/sdk/ContentFeedsDataDictionary/exceptions.py
fds/sdk/ContentFeedsDataDictionary/model_utils.py
fds/sdk/ContentFeedsDataDictionary/rest.py
fds/sdk/ContentFeedsDataDictionary/api/__init__.py
fds/sdk/ContentFeedsDataDictionary/api/navigator_api.py
fds/sdk/ContentFeedsDataDictionary/apis/__init__.py
fds/sdk/ContentFeedsDataDictionary/model/__init__.py
fds/sdk/ContentFeedsDataDictionary/model/api_endpoint.py
fds/sdk/ContentFeedsDataDictionary/model/basic_search_request.py
fds/sdk/ContentFeedsDataDictionary/model/basic_search_response.py
fds/sdk/ContentFeedsDataDictionary/model/basic_search_response_results.py
fds/sdk/ContentFeedsDataDictionary/model/data_item.py
fds/sdk/ContentFeedsDataDictionary/model/navigator_sources_response.py
fds/sdk/ContentFeedsDataDictionary/model/product.py
fds/sdk/ContentFeedsDataDictionary/model/reference_group.py
fds/sdk/ContentFeedsDataDictionary/model/table.py
fds/sdk/ContentFeedsDataDictionary/model/table_code_field_info_response.py
fds/sdk/ContentFeedsDataDictionary/model/table_code_info.py
fds/sdk/ContentFeedsDataDictionary/model/table_field.py
fds/sdk/ContentFeedsDataDictionary/models/__init__.py
fds.sdk.ContentFeedsDataDictionary-0.21.15.dist-info/LICENSE
fds.sdk.ContentFeedsDataDictionary-0.21.15.dist-info/METADATA
fds.sdk.ContentFeedsDataDictionary-0.21.15.dist-info/WHEEL
fds.sdk.ContentFeedsDataDictionary-0.21.15.dist-info/top_level.txt
fds.sdk.ContentFeedsDataDictionary-0.21.15.dist-info/RECORD
